{"cameraMode":{"drawMode":0,"name":"Shaded","section":"Shading Mode"},"sceneLighting":true,"audioPlay":false,"sceneViewState":{"m_AlwaysRefresh":false,"showFog":true,"showSkybox":true,"showFlares":true,"showImageEffects":true,"showParticleSystems":true,"showVisualEffectGraphs":true,"m_FxEnabled":true},"in2DMode":false,"pivot":{"x":401.97576904296877,"y":-720.5264282226563,"z":-938.49853515625},"rotation":{"x":-0.03596147894859314,"y":-0.9422399997711182,"z":0.31519344449043276,"w":-0.1076146736741066},"size":3277.509521484375,"orthographic":false}